README.rst
setup.py
lima/__init__.py
lima/abc.py
lima/exc.py
lima/fields.py
lima/registry.py
lima/schema.py
lima/util.py
lima.egg-info/PKG-INFO
lima.egg-info/SOURCES.txt
lima.egg-info/dependency_links.txt
lima.egg-info/top_level.txt
lima.egg-info/zip-safe