Metadata-Version: 1.1
Name: lima
Version: 0.4
Summary: Lightweight Marshalling of Python 3 Objects.
Home-page: https://lima.readthedocs.org
Author: Bernhard Weitzhofer
Author-email: bernhard@weitzhofer.org
License: MIT License
Keywords: marshal marshalling serialization api json rest
Platform: UNKNOWN
Classifier: Development Status :: 4 - Beta
Classifier: Environment :: Web Environment
Classifier: Intended Audience :: Developers
Classifier: License :: DFSG approved
Classifier: License :: OSI Approved :: MIT License
Classifier: Natural Language :: English
Classifier: Operating System :: OS Independent
Classifier: Programming Language :: Python :: 3
Classifier: Programming Language :: Python :: 3.3
Classifier: Programming Language :: Python :: 3.4
Classifier: Topic :: Software Development :: Libraries :: Python Modules
